binance/__init__.py
binance/ccxt/__init__.py
binance/ccxt/binance.py
binance/ccxt/abstract/binance.py
binance/ccxt/async_support/__init__.py
binance/ccxt/async_support/binance.py
binance/ccxt/async_support/base/__init__.py
binance/ccxt/async_support/base/exchange.py
binance/ccxt/async_support/base/throttler.py
binance/ccxt/async_support/base/ws/__init__.py
binance/ccxt/async_support/base/ws/cache.py
binance/ccxt/async_support/base/ws/client.py
binance/ccxt/async_support/base/ws/functions.py
binance/ccxt/async_support/base/ws/future.py
binance/ccxt/async_support/base/ws/order_book.py
binance/ccxt/async_support/base/ws/order_book_side.py
binance/ccxt/base/__init__.py
binance/ccxt/base/decimal_to_precision.py
binance/ccxt/base/errors.py
binance/ccxt/base/exchange.py
binance/ccxt/base/precise.py
binance/ccxt/base/types.py
binance/ccxt/pro/__init__.py
binance/ccxt/pro/binance.py
binance/ccxt/static_dependencies/README.md
binance/ccxt/static_dependencies/__init__.py
binance/ccxt/static_dependencies/bip/__init__.py
binance/ccxt/static_dependencies/bip/addr/P2PKH_addr.py
binance/ccxt/static_dependencies/bip/addr/__init__.py
binance/ccxt/static_dependencies/bip/addr/addr_dec_utils.py
binance/ccxt/static_dependencies/bip/addr/addr_key_validator.py
binance/ccxt/static_dependencies/bip/addr/iaddr_decoder.py
binance/ccxt/static_dependencies/bip/addr/iaddr_encoder.py
binance/ccxt/static_dependencies/bip/base58/__init__.py
binance/ccxt/static_dependencies/bip/base58/base58.py
binance/ccxt/static_dependencies/bip/base58/base58_ex.py
binance/ccxt/static_dependencies/bip/base58/base58_xmr.py
binance/ccxt/static_dependencies/bip/bech32/__init__.py
binance/ccxt/static_dependencies/bip/bech32/bch_bech32.py
binance/ccxt/static_dependencies/bip/bech32/bech32.py
binance/ccxt/static_dependencies/bip/bech32/bech32_base.py
binance/ccxt/static_dependencies/bip/bech32/bech32_ex.py
binance/ccxt/static_dependencies/bip/bech32/segwit_bech32.py
binance-0.3.101.dist-info/METADATA
binance-0.3.101.dist-info/WHEEL
binance-0.3.101.dist-info/RECORD
